gocheck/__init__.py
gocheck/image_distortion.py
gocheck-0.1.3.dist-info/LICENSE
gocheck-0.1.3.dist-info/METADATA
gocheck-0.1.3.dist-info/WHEEL
gocheck-0.1.3.dist-info/top_level.txt
gocheck-0.1.3.dist-info/RECORD
