Metadata-Version: 2.1
Name: gocheck
Version: 0.1.3
Summary: A Python library for barrel distortion correction in wide-angle images
Home-page: https://github.com/jujuspace/gocheck
Author: jujuspace
Author-email: juseongparkai@gmail.com
License: Copyright (c) 2025 jujuspace
Project-URL: Homepage, https://github.com/jujuspace/gocheck
Project-URL: Repository, https://github.com/jujuspace/gocheck
Project-URL: Issues, https://github.com/jujuspace/gocheck/issues
Keywords: image processing,distortion correction,barrel distortion,opencv,computer vision
Classifier: Development Status :: 3 - Alpha
Classifier: Intended Audience :: Developers
Classifier: License :: OSI Approved :: MIT License
Classifier: Operating System :: OS Independent
Classifier: Programming Language :: Python :: 3
Classifier: Programming Language :: Python :: 3.7
Classifier: Programming Language :: Python :: 3.8
Classifier: Programming Language :: Python :: 3.9
Classifier: Programming Language :: Python :: 3.10
Classifier: Programming Language :: Python :: 3.11
Classifier: Topic :: Scientific/Engineering :: Image Processing
Classifier: Topic :: Multimedia :: Graphics :: Graphics Conversion
Requires-Python: >=3.7
License-File: LICENSE
Requires-Dist: opencv-python >=4.5.0
Requires-Dist: numpy >=1.19.0
